plato/__init__.py
plato/audit_ui.py
plato/cli.py
plato/config.py
plato/exceptions.py
plato/flow_executor.py
plato/libplato.dylib
plato/sandbox_sdk.py
plato/sdk.py
plato/sync_env.py
plato/sync_flow_executor.py
plato/sync_sdk.py
plato/bin/plato-cli
plato/bin/proxytunnel-darwin-amd64
plato/examples/doordash_tasks.py
plato/examples/loadtest.py
plato/examples/test_env.py
plato/examples/test_env_custom_browser.py
plato/examples/test_env_sync.py
plato/examples/test_reuse_env.py
plato/examples/test_run.py
plato/examples/test_sandbox_sdk.py
plato/flows/db_logins.py
plato/flows/akaunting/scripts.yaml
plato/flows/bugsink/scripts.yaml
plato/flows/calcom/scripts.yaml
plato/flows/discourse/scripts.yaml
plato/flows/dolibarr/scripts.yaml
plato/flows/doordash/scripts.yaml
plato/flows/elasticsearch/scripts.yaml
plato/flows/espocrm/scripts.yaml
plato/flows/firefly/scripts.yaml
plato/flows/fleetbase/scripts.yaml
plato/flows/frappebuilder/scripts.yaml
plato/flows/frappecrm/scripts.yaml
plato/flows/frappeeducation/scripts.yaml
plato/flows/frappeerpnext/scripts.yaml
plato/flows/frappehelpdesk/scripts.yaml
plato/flows/frappeinsights/scripts.yaml
plato/flows/frappelms/scripts.yaml
plato/flows/frappewiki/scripts.yaml
plato/flows/getcalfresh/scripts.yaml
plato/flows/gitlab/scripts.yaml
plato/flows/grafana/scripts.yaml
plato/flows/invoiceninja/scripts.yaml
plato/flows/jenkins/scripts.yaml
plato/flows/kanboard/scripts.yaml
plato/flows/ledgersmb/scripts.yaml
plato/flows/listmonk/scripts.yaml
plato/flows/mattermost/scripts.yaml
plato/flows/mealie/scripts.yaml
plato/flows/metabase/scripts.yaml
plato/flows/moodle/scripts.yaml
plato/flows/nextcloud/scripts.yaml
plato/flows/nginx-basic/scripts.yaml
plato/flows/odoo/scripts.yaml
plato/flows/odooattendances/scripts.yaml
plato/flows/odoocrm/scripts.yaml
plato/flows/odoodatarecycle/scripts.yaml
plato/flows/odooelearning/scripts.yaml
plato/flows/odooemailmarketing/scripts.yaml
plato/flows/odooemployees/scripts.yaml
plato/flows/odooevents/scripts.yaml
plato_sdk-1.3.3.dist-info/METADATA
plato_sdk-1.3.3.dist-info/WHEEL
plato_sdk-1.3.3.dist-info/entry_points.txt
plato_sdk-1.3.3.dist-info/top_level.txt
plato_sdk-1.3.3.dist-info/RECORD
