Metadata-Version: 2.4
Name: plato-sdk
Version: 1.3.3
Summary: Plato SDK
Author-email: Pranav Putta <pranav@plato.so>, Rob Farlow <rob@plato.so>
Requires-Python: >=3.10
Requires-Dist: aiohttp>=3.11.13
Requires-Dist: openai>=1.70.0
Requires-Dist: pydantic>=2.10.6
Requires-Dist: pydantic-settings>=2.8.1
Requires-Dist: click>=8.0.0
Requires-Dist: python-dotenv>=0.19.0
Requires-Dist: aioboto3>=15.0.0
Requires-Dist: pyyaml>=6.0.2
Requires-Dist: requests>=2.32.4
Requires-Dist: boto3>=1.38.27
Requires-Dist: typer>=0.17.4
Requires-Dist: playwright>=1.50.0
Requires-Dist: streamlit>=1.32.0
Requires-Dist: psycopg2-binary>=2.9.9
Requires-Dist: pymysql>=1.1.1
